volatildap/__init__.py
volatildap/cli.py
volatildap/control.py
volatildap/core.py
volatildap/server.py
volatildap-1.5.0.dist-info/LICENSE
volatildap-1.5.0.dist-info/METADATA
volatildap-1.5.0.dist-info/WHEEL
volatildap-1.5.0.dist-info/top_level.txt
volatildap-1.5.0.dist-info/RECORD
