Metadata-Version: 2.1
Name: volatildap
Version: 1.5.0
Summary: Temporary slapd launcher for testing purposes
Home-page: https://github.com/rbarrois/volatildap
Author: Raphaël Barrois
Author-email: raphael.barrois+volatildap@polytechnique.org
License: BSD
Keywords: ldap,test,openldap,slapd
Platform: UNKNOWN
Classifier: Development Status :: 5 - Production/Stable
Classifier: Intended Audience :: Developers
Classifier: License :: OSI Approved :: BSD License
Classifier: Operating System :: Unix
Classifier: Programming Language :: Python
Classifier: Programming Language :: Python :: 3.6
Classifier: Programming Language :: Python :: 3.7
Classifier: Programming Language :: Python :: 3.8
Classifier: Programming Language :: Python :: Implementation :: CPython
Classifier: Programming Language :: Python :: Implementation :: PyPy
Classifier: Topic :: Software Development
Classifier: Topic :: Software Development :: Testing
Classifier: Topic :: System :: Systems Administration :: Authentication/Directory :: LDAP
Requires-Python: >=3.5
Requires-Dist: requests
Provides-Extra: dev
Requires-Dist: check-manifest ; extra == 'dev'
Requires-Dist: flake8 ; extra == 'dev'
Requires-Dist: isort (>=5.0.0) ; extra == 'dev'
Requires-Dist: tox ; extra == 'dev'
Requires-Dist: psutil ; extra == 'dev'
Requires-Dist: wheel ; extra == 'dev'
Requires-Dist: zest.releaser[recommended] ; extra == 'dev'
